{"timestamp": "2026-07-17 00:31:00", "members": {"MY | Kosuke Ueki X": 0, "Tears": 7608, "MY | iMuiz": 2278, "Sugar Talking": 5337, "MY | iMuiz X": 1993, "2": 7433, "warrior": 2802, "CatDile": 1229, "My Man on Willpower": 5179, "Nasi Goreng Kampung": 0, "OROCHIMARU": 7888, "Mahsuri": 22956, "MY | Player 006": 370, "MY | Player 007": 370, "MY | Player 008": 360, "MY | Player 009": 366, "MY | Player 010": 362, "Parameswara": 22166, "Hang Tuah": 21348, "Mahawangsa": 20585, "Tun Teja": 19894, "Elavoth": 24077, "Dracoth": 23347, "Summoth": 22476, "Maximoth": 21612, "MY | Player 001": 1138, "Shadow": 23980, "Assassin": 23214, "Zenith": 22344, "Astraphel": 21463, "Noir": 20593, "MY | Naruke": 0, "Jork": 3116, "Lotus": 70, "Deucedrag": 493, "iZengotsou": 0, "Heracoth": 20843, "MY | Player 002": 1098, "MY | Player 003": 945, "Player (#1)": 2815, "Player (#2)": 2597, "yatoro": 17041, "Ryugai": 0, "PuNch": 11010, "\u00a7hitnobi (#1)": 0, "\u00a7hitnobi (#2)": 0, "\u00a7hitnobi (#3)": 0, "\u00a7hitnobi (#4)": 0, "\u00a7hitnobi (#5)": 0, "KOPZ2": 16768, "COPZ1": 17116, "Ryzeee": 13132, "Aluphiee": 13275}}