{"timestamp": "2026-07-03 14:31:00", "members": {"gokito": 0, "MY | Kosuke Ueki X": 0, "Mery": 350, "MY | iMuiz": 575, "GON": 263, "MY | iMuiz X": 439, "2": 435, "warrior": 2372, "CatDile": 446, "Eucresia X": 285, "Nasi Goreng Kampung": 0, "OROCHIMARU": 1681, "Mahsuri": 4100, "MY | Player 006": 0, "MY | Player 007": 0, "MY | Player 008": 0, "MY | Player 009": 0, "MY | Player 010": 0, "Parameswara": 3958, "Hang Tuah": 3825, "Mahawangsa": 3660, "Tun Teja": 3579, "Elavoth": 4241, "Dracoth": 4075, "Summoth": 3886, "Maximoth": 3690, "MY | Player 001": 55, "Shadow": 3865, "Assassin": 3848, "Zenith": 3552, "Astraphel": 3414, "Noir": 3247, "MY | Naruke": 0, "Jork": 466, "Lotus": 70, "Deucedrag": 288, "iZengotsou": 0, "Heracoth": 3554, "MY | Player 002": 75, "MY | Player 003": 75, "Player": 0, "yatoro": 2413, "Ryugai": 0, "PuNch": 2549, "\u00a7hitnobi": 2221, "KOPZ2": 2359, "COPZ1": 2396, "Ryzeee": 2481, "Aluphiee": 2602}}