{"timestamp": "2026-07-16 15:31:00", "members": {"MY | Kosuke Ueki X": 0, "Tears": 7608, "MY | iMuiz": 2278, "Sugar Talking": 5337, "MY | iMuiz X": 1993, "2": 7433, "warrior": 2802, "CatDile": 1229, "My Man on Willpower": 5179, "Nasi Goreng Kampung": 0, "OROCHIMARU": 7888, "Mahsuri": 22446, "MY | Player 006": 370, "MY | Player 007": 370, "MY | Player 008": 360, "MY | Player 009": 366, "MY | Player 010": 362, "Parameswara": 21706, "Hang Tuah": 20923, "Mahawangsa": 20160, "Tun Teja": 19469, "Elavoth": 23581, "Dracoth": 22892, "Summoth": 22051, "Maximoth": 21187, "MY | Player 001": 1138, "Shadow": 23415, "Assassin": 22744, "Zenith": 21904, "Astraphel": 21038, "Noir": 20168, "MY | Naruke": 0, "Jork": 3116, "Lotus": 70, "Deucedrag": 443, "iZengotsou": 0, "Heracoth": 20418, "MY | Player 002": 1098, "MY | Player 003": 945, "Player (#1)": 2815, "Player (#2)": 2597, "yatoro": 16520, "Ryugai": 0, "PuNch": 10385, "\u00a7hitnobi (#1)": 0, "\u00a7hitnobi (#2)": 0, "\u00a7hitnobi (#3)": 0, "\u00a7hitnobi (#4)": 0, "\u00a7hitnobi (#5)": 0, "KOPZ2": 16271, "COPZ1": 16540, "Ryzeee": 12802, "Aluphiee": 12965}}