{"timestamp": "2026-07-19 14:01:00", "members": {"MY | Kosuke Ueki X": 0, "Tears": 0, "MY | iMuiz": 0, "Sugar Talking": 0, "MY | iMuiz X": 0, "2": 0, "warrior": 0, "CatDile": 0, "My Man on Willpower": 0, "Nasi Goreng Kampung": 0, "OROCHIMARU": 0, "Mahsuri": 0, "MY | Player 006": 0, "MY | Player 007": 0, "MY | Player 008": 0, "MY | Player 009": 0, "MY | Player 010": 0, "Parameswara": 0, "Hang Tuah": 0, "Mahawangsa": 0, "Tun Teja": 0, "Elavoth": 0, "Dracoth": 0, "Summoth": 0, "Maximoth": 0, "MY | Player 001": 0, "Shadow": 0, "Assassin": 0, "Zenith": 0, "Astraphel": 0, "Noir": 0, "MY | Naruke": 0, "Jork": 0, "Lotus": 0, "Deucedrag": 0, "Ripley": 0, "iZengotsou": 0, "Heracoth": 0, "MY | Player 002": 0, "MY | Player 003": 0, "Player (#1)": 0, "R\u00c4\u201c\u00cf\u2021 \u00e2\u20ac\u00a2 \u00c2\u00a2\u00e2\u201e\u201c\u00ce\u00b1\u00ce\u00b7\u00c2\u00a2\u00d1\u0192": 0, "Player (#2)": 0, "yatoro": 0, "Ryugai": 0, "PuNch": 0, "\u00a7hitnobi (#1)": 0, "\u00a7hitnobi (#2)": 0, "\u00a7hitnobi (#3)": 0, "\u00a7hitnobi (#4)": 0, "\u00a7hitnobi (#5)": 0, "KOPZ2": 0, "COPZ1": 0, "Ryzeee": 0, "Aluphiee": 0}, "order": ["MY | Kosuke Ueki X", "Tears", "MY | iMuiz", "Sugar Talking", "MY | iMuiz X", "2", "warrior", "CatDile", "My Man on Willpower", "Nasi Goreng Kampung", "OROCHIMARU", "Mahsuri", "MY | Player 006", "MY | Player 007", "MY | Player 008", "MY | Player 009", "MY | Player 010", "Parameswara", "Hang Tuah", "Mahawangsa", "Tun Teja", "Elavoth", "Dracoth", "Summoth", "Maximoth", "MY | Player 001", "Shadow", "Assassin", "Zenith", "Astraphel", "Noir", "MY | Naruke", "Jork", "Lotus", "Deucedrag", "Ripley", "iZengotsou", "Heracoth", "MY | Player 002", "MY | Player 003", "Player (#1)", "R\u00c4\u201c\u00cf\u2021 \u00e2\u20ac\u00a2 \u00c2\u00a2\u00e2\u201e\u201c\u00ce\u00b1\u00ce\u00b7\u00c2\u00a2\u00d1\u0192", "Player (#2)", "yatoro", "Ryugai", "PuNch", "\u00a7hitnobi (#1)", "\u00a7hitnobi (#2)", "\u00a7hitnobi (#3)", "\u00a7hitnobi (#4)", "\u00a7hitnobi (#5)", "KOPZ2", "COPZ1", "Ryzeee", "Aluphiee"]}