{"timestamp": "2026-07-20 12:31:00", "members": {"OROCHIMARU": 0, "Mahsuri": 4209, "Parameswara": 4035, "Hang Tuah": 3470, "Mahawangsa": 2890, "Tun Teja": 3123, "Elavoth": 3852, "Dracoth": 3760, "Summoth": 3770, "Maximoth": 3005, "Shadow": 4090, "Assassin": 3952, "Zenith": 3662, "Astraphel": 3440, "Noir": 3196, "Deucedrag": 0, "Heracoth": 2769}, "order": ["OROCHIMARU", "Mahsuri", "Parameswara", "Hang Tuah", "Mahawangsa", "Tun Teja", "Elavoth", "Dracoth", "Summoth", "Maximoth", "Shadow", "Assassin", "Zenith", "Astraphel", "Noir", "Deucedrag", "Heracoth"]}