{"timestamp": "2026-07-09 21:01:00", "members": {"MY | Kosuke Ueki X": 0, "Tears": 4453, "MY | iMuiz": 1853, "Sugar Talking": 2471, "MY | iMuiz X": 1576, "2": 5137, "warrior": 2802, "CatDile": 699, "My Man on Willpower": 2403, "Nasi Goreng Kampung": 0, "OROCHIMARU": 5017, "Mahsuri": 13461, "MY | Player 006": 370, "MY | Player 007": 370, "MY | Player 008": 360, "MY | Player 009": 366, "MY | Player 010": 362, "Parameswara": 12906, "Hang Tuah": 12228, "Mahawangsa": 11395, "Tun Teja": 10809, "Elavoth": 13176, "Dracoth": 12652, "Summoth": 11921, "Maximoth": 11062, "MY | Player 001": 1138, "Shadow": 12950, "Assassin": 12441, "Zenith": 11694, "Astraphel": 10978, "Noir": 10248, "MY | Naruke": 0, "Jork": 1811, "Lotus": 70, "Deucedrag": 393, "iZengotsou": 0, "Heracoth": 10347, "MY | Player 002": 1098, "MY | Player 003": 945, "Player (#1)": 2815, "Player (#2)": 1265, "yatoro": 7875, "Ryugai": 0, "PuNch": 5752, "\u00a7hitnobi (#1)": 4145, "\u00a7hitnobi (#2)": 4082, "\u00a7hitnobi (#3)": 4101, "\u00a7hitnobi (#4)": 5930, "\u00a7hitnobi (#5)": 5848, "KOPZ2": 7774, "COPZ1": 7865, "Ryzeee": 6297, "Aluphiee": 6479}}