{"timestamp": "2026-07-03 22:01:00", "members": {"gokito": 0, "MY | Kosuke Ueki X": 0, "Mery": 705, "MY | iMuiz": 575, "GON": 263, "MY | iMuiz X": 439, "2": 453, "warrior": 2722, "CatDile": 471, "Eucresia X": 285, "Nasi Goreng Kampung": 0, "OROCHIMARU": 1978, "Mahsuri": 4475, "MY | Player 006": 0, "MY | Player 007": 0, "MY | Player 008": 0, "MY | Player 009": 0, "MY | Player 010": 0, "Parameswara": 4333, "Hang Tuah": 4200, "Mahawangsa": 4035, "Tun Teja": 3944, "Elavoth": 4616, "Dracoth": 4450, "Summoth": 4261, "Maximoth": 4065, "MY | Player 001": 55, "Shadow": 4240, "Assassin": 4223, "Zenith": 3927, "Astraphel": 3789, "Noir": 3614, "MY | Naruke": 0, "Jork": 466, "Lotus": 70, "Deucedrag": 288, "iZengotsou": 0, "Heracoth": 3919, "MY | Player 002": 75, "MY | Player 003": 75, "Player": 0, "yatoro": 2763, "Ryugai": 0, "PuNch": 2914, "\u00a7hitnobi": 2542, "KOPZ2": 2709, "COPZ1": 2746, "Ryzeee": 2756, "Aluphiee": 2877}}